petaldata/__init__.py
petaldata/util.py
petaldata/datasets/__init__.py
petaldata/datasets/abstract/__init__.py
petaldata/datasets/abstract/dataset.py
petaldata/datasets/hubspot/__init__.py
petaldata/datasets/hubspot/contact_old.py
petaldata/datasets/hubspot/contacts.py
petaldata/datasets/metabase/__init__.py
petaldata/datasets/metabase/card.py
petaldata/datasets/stripe/__init__.py
petaldata/datasets/stripe/invoices.py
petaldata/datasets/stripe/reports/__init__.py
petaldata/datasets/stripe/reports/abstract_stripe_report.py
petaldata/datasets/stripe/reports/adjusted_invoices.py
petaldata/datasets/stripe/reports/mrr_by_month.py
petaldata/datasets/stripe/reports/mtd_revenue.py
petaldata/datasets/stripe/reports/query_filters.py
petaldata/datasets/stripe/reports/revenue_by_plan_by_month.py
petaldata/datasets/stripe/reports/summary.py
petaldata/datasets/stripe/reports/customer_lists/__init__.py
petaldata/datasets/stripe/reports/customer_lists/abstract_mom_diff.py
petaldata/datasets/stripe/reports/customer_lists/churned.py
petaldata/datasets/stripe/reports/customer_lists/expansion_contraction.py
petaldata/datasets/stripe/reports/customer_lists/new.py
petaldata/resource/__init__.py
petaldata/resource/abstract/__init__.py
petaldata/resource/abstract/resource.py
petaldata/resource/hubspot/__init__.py
petaldata/resource/hubspot/contact.py
petaldata/resource/stripe/__init__.py
petaldata/resource/stripe/invoice.py
petaldata/resource/stripe/reports/__init__.py
petaldata/resource/stripe/reports/abstract_stripe_report.py
petaldata/resource/stripe/reports/mrr_by_month.py
petaldata/resource/stripe/reports/query_filters.py
petaldata/storage/__init__.py
petaldata/storage/abstract_storage.py
petaldata/storage/local.py
petaldata/storage/s3.py
petaldata-1.0.2.dist-info/LICENSE
petaldata-1.0.2.dist-info/METADATA
petaldata-1.0.2.dist-info/WHEEL
petaldata-1.0.2.dist-info/top_level.txt
petaldata-1.0.2.dist-info/RECORD
