Metadata-Version: 2.1
Name: petaldata
Version: 1.0.2
Summary: Export your data from cloud apps like Stripe, Hubspot, and Metabase into Pandas Dataframes.
Home-page: https://github.com/petaldata/petaldata-python
Author: Derek Haynes
Author-email: derek@petaldata.com
License: UNKNOWN
Platform: UNKNOWN
Classifier: Programming Language :: Python :: 3
Classifier: License :: OSI Approved :: MIT License
Classifier: Operating System :: OS Independent
Requires-Dist: pandas
Requires-Dist: numpy
Requires-Dist: requests
Requires-Dist: smart-open
Requires-Dist: boto3
Requires-Dist: pygsheets
